async_lru/__init__.py
async_lru/py.typed
async_lru-2.0.3.dist-info/LICENSE
async_lru-2.0.3.dist-info/METADATA
async_lru-2.0.3.dist-info/WHEEL
async_lru-2.0.3.dist-info/top_level.txt
async_lru-2.0.3.dist-info/RECORD
