Metadata-Version: 2.1
Name: async-lru
Version: 2.0.3
Summary: Simple LRU cache for asyncio
Home-page: https://github.com/aio-libs/async-lru
Maintainer: aiohttp team <team@aiohttp.org>
Maintainer-email: team@aiohttp.org
License: MIT License
Project-URL: Chat: Matrix, https://matrix.to/#/#aio-libs:matrix.org
Project-URL: Chat: Matrix Space, https://matrix.to/#/#aio-libs-space:matrix.org
Project-URL: CI: GitHub Actions, https://github.com/aio-libs/async-lru/actions
Project-URL: GitHub: repo, https://github.com/aio-libs/async-lru
Keywords: asyncio,lru,lru_cache
Classifier: License :: OSI Approved :: MIT License
Classifier: Intended Audience :: Developers
Classifier: Programming Language :: Python
Classifier: Programming Language :: Python :: 3
Classifier: Programming Language :: Python :: 3 :: Only
Classifier: Programming Language :: Python :: 3.8
Classifier: Programming Language :: Python :: 3.9
Classifier: Programming Language :: Python :: 3.10
Classifier: Programming Language :: Python :: 3.11
Classifier: Development Status :: 5 - Production/Stable
Classifier: Framework :: AsyncIO
Requires-Python: >=3.8
License-File: LICENSE
